subtractor2/full_subtractor.v
module full_subtractor (
    input A,
    input B,
    input Bin,
    output Diff,
    output Borrow
);

assign Diff   = A ^ B ^ Bin;
assign Borrow = (~A & B) | (~A & Bin) | (B & Bin);

endmodule

subtractor2/full_subtractor_tb.v
`timescale 1ns/1ns

module full_subtractor_tb;

reg A, B, Bin;
wire Diff, Borrow;

full_subtractor uut (
    .A(A),
    .B(B),
    .Bin(Bin),
    .Diff(Diff),
    .Borrow(Borrow)
);

initial begin
    $display("A B Bin | Diff Borrow");
    $display("---------------------");

    A=0; B=0; Bin=0; #10;
    $display("%b %b  %b  |   %b     %b", A,B,Bin,Diff,Borrow);

    A=0; B=0; Bin=1; #10;
    $display("%b %b  %b  |   %b     %b", A,B,Bin,Diff,Borrow);

    A=0; B=1; Bin=0; #10;
    $display("%b %b  %b  |   %b     %b", A,B,Bin,Diff,Borrow);

    A=0; B=1; Bin=1; #10;
    $display("%b %b  %b  |   %b     %b", A,B,Bin,Diff,Borrow);

    A=1; B=0; Bin=0; #10;
    $display("%b %b  %b  |   %b     %b", A,B,Bin,Diff,Borrow);

    A=1; B=0; Bin=1; #10;
    $display("%b %b  %b  |   %b     %b", A,B,Bin,Diff,Borrow);

    A=1; B=1; Bin=0; #10;
    $display("%b %b  %b  |   %b     %b", A,B,Bin,Diff,Borrow);

    A=1; B=1; Bin=1; #10;
    $display("%b %b  %b  |   %b     %b", A,B,Bin,Diff,Borrow);

    $finish;
end

initial begin
    $dumpfile("full_subtractor.vcd");
    $dumpvars(0, full_subtractor_tb);
end

endmodule

subtractor2/full_subtractor.vcd
$date
	Fri Apr 24 15:57:25 2026
$end
$version
	Icarus Verilog
$end
$timescale
	1ns
$end
$scope module full_subtractor_tb $end
$var wire 1 ! Diff $end
$var wire 1 " Borrow $end
$var reg 1 # A $end
$var reg 1 $ B $end
$var reg 1 % Bin $end
$scope module uut $end
$var wire 1 # A $end
$var wire 1 $ B $end
$var wire 1 % Bin $end
$var wire 1 " Borrow $end
$var wire 1 ! Diff $end
$upscope $end
$upscope $end
$enddefinitions $end
$comment Show the parameter values. $end
$dumpall
$end
#0
$dumpvars
0%
0$
0#
0"
0!
$end
#10
1"
1!
1%
#20
0%
1$
#30
0!
1%
#40
0"
1!
0%
0$
1#
#50
0!
1%
#60
0%
1$
#70
1"
1!
1%
